tiered_debug/__init__.py
tiered_debug/_base.py
tiered_debug/debug.py
tiered_debug/py.typed
tiered_debug-1.4.0.dist-info/METADATA
tiered_debug-1.4.0.dist-info/WHEEL
tiered_debug-1.4.0.dist-info/licenses/LICENSE
tiered_debug-1.4.0.dist-info/RECORD
