Metadata-Version: 2.4
Name: tiered-debug
Version: 1.4.0
Summary: A Python logging helper module that allows multiple levels of debug logging
Project-URL: Homepage, https://github.com/untergeek/tiered-debug
Project-URL: Bug Tracker, https://github.com/untergeek/tiered-debug/issues
Project-URL: Issues, https://github.com/untergeek/tiered-debug/issues
Project-URL: Documentation, https://tiered-debug.readthedocs.io/
Project-URL: Source, https://github.com/untergeek/tiered-debug
Project-URL: Release Notes, https://github.com/untergeek/tiered-debug/releases
Author-email: Aaron Mildenstein <aaron@mildensteins.com>
License: Apache-2.0
License-File: LICENSE
Keywords: debug,logging,tiered-debug
Classifier: Development Status :: 4 - Beta
Classifier: Programming Language :: Python
Classifier: Programming Language :: Python :: 3.8
Classifier: Programming Language :: Python :: 3.9
Classifier: Programming Language :: Python :: 3.10
Classifier: Programming Language :: Python :: 3.11
Classifier: Programming Language :: Python :: 3.12
Classifier: Programming Language :: Python :: 3.13
Requires-Python: >=3.8
Provides-Extra: doc
Requires-Dist: sphinx; extra == 'doc'
Requires-Dist: sphinx-rtd-theme; extra == 'doc'
Provides-Extra: test
Requires-Dist: pytest-cov; extra == 'test'
Requires-Dist: pytest>=7.2.1; extra == 'test'
